enjoy_slurm/__init__.py
enjoy_slurm/_version.py
enjoy_slurm/config.py
enjoy_slurm/parser.py
enjoy_slurm/slurm.py
enjoy_slurm/tutorial.py
enjoy_slurm/utils.py
tests/__init__.py
tests/test_job.py
tests/test_parser.py
tests/test_slurm.py
tests/test_tutorial.py
tests/test_utils.py
tests/test_with_slurm.py
enjoy_slurm-0.1.3.dist-info/LICENSE.txt
enjoy_slurm-0.1.3.dist-info/METADATA
enjoy_slurm-0.1.3.dist-info/WHEEL
enjoy_slurm-0.1.3.dist-info/top_level.txt
enjoy_slurm-0.1.3.dist-info/RECORD
